odoo/addons/stock_picking_purchase_propagate/README.rst
odoo/addons/stock_picking_purchase_propagate/__init__.py
odoo/addons/stock_picking_purchase_propagate/__manifest__.py
odoo/addons/stock_picking_purchase_propagate/i18n/pt_BR.po
odoo/addons/stock_picking_purchase_propagate/i18n/stock_picking_purchase_propagate.pot
odoo/addons/stock_picking_purchase_propagate/models/__init__.py
odoo/addons/stock_picking_purchase_propagate/models/purchase.py
odoo/addons/stock_picking_purchase_propagate/models/stock_move.py
odoo/addons/stock_picking_purchase_propagate/readme/CONTRIBUTORS.rst
odoo/addons/stock_picking_purchase_propagate/readme/DESCRIPTION.rst
odoo/addons/stock_picking_purchase_propagate/readme/USAGE.rst
odoo/addons/stock_picking_purchase_propagate/static/description/icon.png
odoo/addons/stock_picking_purchase_propagate/static/description/index.html
odoo/addons/stock_picking_purchase_propagate/tests/__init__.py
odoo/addons/stock_picking_purchase_propagate/tests/test_po_propagate.py
odoo12_addon_stock_picking_purchase_propagate-12.0.1.0.0.99.dev6.dist-info/METADATA
odoo12_addon_stock_picking_purchase_propagate-12.0.1.0.0.99.dev6.dist-info/WHEEL
odoo12_addon_stock_picking_purchase_propagate-12.0.1.0.0.99.dev6.dist-info/top_level.txt
odoo12_addon_stock_picking_purchase_propagate-12.0.1.0.0.99.dev6.dist-info/RECORD
